syphon/__init__.py
syphon/__main__.py
syphon/_cmdparser.py
syphon/_version.py
syphon/errors.py
syphon/hash.py
syphon/core/__init__.py
syphon/core/build.py
syphon/core/check.py
syphon/core/init.py
syphon/core/archive/__init__.py
syphon/core/archive/archive.py
syphon/core/archive/datafilter.py
syphon/core/archive/filemap.py
syphon/core/archive/lockmanager.py
syphon/schema/__init__.py
syphon/schema/checkcolumns.py
syphon/schema/load.py
syphon/schema/resolvepath.py
syphon/schema/save.py
tests/__init__.py
tests/assert_utils.py
tests/conftest.py
tests/test_main.py
tests/types.py
tests/core/__init__.py
tests/core/conftest.py
tests/core/test_build.py
tests/core/test_check.py
tests/core/test_init.py
tests/core/archive/__init__.py
tests/core/archive/test_archive.py
tests/core/archive/test_datafilter.py
tests/core/archive/test_filemap.py
tests/core/archive/test_lockmanager.py
tests/hash/__init__.py
tests/hash/conftest.py
tests/hash/test_hashentry.py
tests/hash/test_hashfile.py
tests/hash/test_openhashfile.py
tests/schema/__init__.py
tests/schema/test_checkcolumns.py
tests/schema/test_load.py
tests/schema/test_resolvepath.py
tests/schema/test_save.py
syphon-2.0.1.dist-info/LICENSE
syphon-2.0.1.dist-info/METADATA
syphon-2.0.1.dist-info/WHEEL
syphon-2.0.1.dist-info/entry_points.txt
syphon-2.0.1.dist-info/top_level.txt
syphon-2.0.1.dist-info/RECORD
