Metadata-Version: 2.1
Name: syphon
Version: 2.0.1
Summary: A CSV data storage and management engine.
Home-page: https://github.com/tektronix/syphon
Author: Evan Hall
Maintainer: Keithley Instruments, LLC. et al.
License: MIT
Project-URL: Source, https://github.com/tektronix/syphon
Project-URL: Tracker, https://github.com/tektronix/syphon/issues
Platform: UNKNOWN
Classifier: Development Status :: 5 - Production/Stable
Classifier: Environment :: Console
Classifier: Intended Audience :: Science/Research
Classifier: License :: OSI Approved :: MIT License
Classifier: Operating System :: Microsoft :: Windows
Classifier: Operating System :: POSIX :: Linux
Classifier: Programming Language :: Python
Classifier: Programming Language :: Python :: 3
Classifier: Programming Language :: Python :: 3.6
Classifier: Programming Language :: Python :: 3.7
Classifier: Topic :: Scientific/Engineering
Classifier: Topic :: Utilities
Requires-Python: >=3,!=3.0.*,!=3.2.*,!=3.3.*,!=3.4.*,!=3.5.*,<4
Requires-Dist: pandas (~=1.0)
Requires-Dist: sortedcontainers (~=2.2)
